bitable_mcp/__init__.py
bitable_mcp/cli.py
bitable_mcp/server.py
mseep_bitable_mcp-0.2.5.dist-info/METADATA
mseep_bitable_mcp-0.2.5.dist-info/WHEEL
mseep_bitable_mcp-0.2.5.dist-info/entry_points.txt
mseep_bitable_mcp-0.2.5.dist-info/top_level.txt
mseep_bitable_mcp-0.2.5.dist-info/RECORD
